EnergyPlusExample/__init__.py
EnergyPlusExample/controller.py
EnergyPlusExample/definitions.py
EnergyPlusExample/energyPlusAPI_Example.py
EnergyPlusExample/federate.py
EnergyPlusExample/gui.py
EnergyPlusExample/main.py
EnergyPlusExample/paraview.py
EnergyPlusExample/server_federate.py
EnergyPlusExample/simulator.py
costmodel-0.2.0.dist-info/METADATA
costmodel-0.2.0.dist-info/WHEEL
costmodel-0.2.0.dist-info/top_level.txt
costmodel-0.2.0.dist-info/RECORD
