Metadata-Version: 2.2
Name: costmodel
Version: 0.2.0
Summary: A cost model application with a Flask web interface.
Home-page: https://github.com/
Author: Edward Honadel and Peter Sandborn
Author-email: ehonadel@umd.edu
License: MIT
Classifier: Programming Language :: Python :: 3
Classifier: Framework :: Flask
Classifier: Operating System :: OS Independent
Requires-Python: >=3.6
Requires-Dist: flask
Requires-Dist: matplotlib
Requires-Dist: plotly
Requires-Dist: pandas
